{
  "unversionedId": "deployment-examples",
  "id": "deployment-examples",
  "title": "Deployment Examples",
  "description": "https:",
  "source": "@site/../docs/deployment-examples.md",
  "sourceDirName": ".",
  "slug": "/deployment-examples",
  "permalink": "/docs/deployment-examples",
  "draft": false,
  "editUrl": "https://github.com/Rookout/docs/edit/master/docs/../docs/deployment-examples.md",
  "tags": [],
  "version": "current",
  "lastUpdatedBy": "Mickael Alliel",
  "lastUpdatedAt": 1543144889,
  "formattedLastUpdatedAt": "Nov 25, 2018",
  "frontMatter": {
    "id": "deployment-examples",
    "title": "Deployment Examples",
    "sidebar_label": "Deployment Examples"
  },
  "sidebar": "introduction",
  "previous": {
    "title": "Go",
    "permalink": "/docs/go-setup"
  },
  "next": {
    "title": "Instances Selection",
    "permalink": "/docs/debug-session-setup"
  }
}